Flask_Application-0.1.0.data/data/.holder
Flask_Application-0.1.0.data/data/__init__.py
Flask_Application-0.1.0.data/data/api.py
Flask_Application-0.1.0.data/data/config.py
Flask_Application-0.1.0.data/data/constants.py
Flask_Application-0.1.0.data/data/favicon.ico
Flask_Application-0.1.0.data/data/gconfig.py
Flask_Application-0.1.0.data/data/home.html
Flask_Application-0.1.0.data/data/index.py
Flask_Application-0.1.0.data/data/manage.py
Flask_Application-0.1.0.data/data/requirements.txt
Flask_Application-0.1.0.data/data/startserver.sh
Flask_Application-0.1.0.data/data/wsgi.py
flask_app/__init__.py
flask_app/templates/app_tmpl/__init__.py
flask_app/templates/app_tmpl/config.py
flask_app/templates/app_tmpl/manage.py
flask_app/templates/app_tmpl/requirements.txt
flask_app/templates/app_tmpl/app/__init__.py
flask_app/templates/app_tmpl/app/controller/__init__.py
flask_app/templates/app_tmpl/app/logs/.holder
flask_app/templates/app_tmpl/app/model/__init__.py
flask_app/templates/app_tmpl/app/static/favicon.ico
flask_app/templates/app_tmpl/app/templates/home.html
flask_app/templates/app_tmpl/app/utils/__init__.py
flask_app/templates/app_tmpl/app/utils/constants.py
flask_app/templates/app_tmpl/app/view/__init__.py
flask_app/templates/app_tmpl/app/view/api.py
flask_app/templates/app_tmpl/app/view/index.py
flask_app/templates/project_tmpl/__init__.py
flask_app/templates/project_tmpl/config.py
flask_app/templates/project_tmpl/gconfig.py
flask_app/templates/project_tmpl/manage.py
flask_app/templates/project_tmpl/requirements.txt
flask_app/templates/project_tmpl/startserver.sh
flask_app/templates/project_tmpl/wsgi.py
flask_app/templates/project_tmpl/apps/__init__.py
flask_app/templates/project_tmpl/apps/app_name/__init__.py
flask_app/templates/project_tmpl/apps/app_name/controller/__init__.py
flask_app/templates/project_tmpl/apps/app_name/model/__init__.py
flask_app/templates/project_tmpl/apps/app_name/templates/home.html
Flask_Application-0.1.0.dist-info/LICENSE
Flask_Application-0.1.0.dist-info/METADATA
Flask_Application-0.1.0.dist-info/WHEEL
Flask_Application-0.1.0.dist-info/entry_points.txt
Flask_Application-0.1.0.dist-info/top_level.txt
Flask_Application-0.1.0.dist-info/RECORD
